Topsis_Parth_102016044/__init__.py
Topsis_Parth_102016044/topsis.py
Topsis_Parth_102016044-0.0.1.dist-info/METADATA
Topsis_Parth_102016044-0.0.1.dist-info/WHEEL
Topsis_Parth_102016044-0.0.1.dist-info/top_level.txt
Topsis_Parth_102016044-0.0.1.dist-info/RECORD
