Metadata-Version: 2.1
Name: Topsis-Parth-102016044
Version: 0.0.1
Summary: Topsis package
Home-page: UNKNOWN
Author: Parth Vohra
Author-email: <pvohra_be20@gmail.com>
License: UNKNOWN
Keywords: python,topsis,machinelearning,datascience
Platform: UNKNOWN
Classifier: Development Status :: 1 - Planning
Classifier: Intended Audience :: Developers
Classifier: Programming Language :: Python :: 3
Classifier: Operating System :: Unix
Classifier: Operating System :: MacOS :: MacOS X
Classifier: Operating System :: Microsoft :: Windows
Requires-Dist: numpy
Requires-Dist: pandas
